menrva/__init__.py
menrva/client.py
menrva/config/client.param.json
menrva/plugins/__init__.py
menrva/plugins/scheduler.py
menrva/plugins/worker.py
menrva-0.0.14.dist-info/METADATA
menrva-0.0.14.dist-info/WHEEL
menrva-0.0.14.dist-info/top_level.txt
menrva-0.0.14.dist-info/RECORD
